README
setup.py
PyProto/__init__.py
PyProto.egg-info/PKG-INFO
PyProto.egg-info/SOURCES.txt
PyProto.egg-info/dependency_links.txt
PyProto.egg-info/top_level.txt
PyProto/eventloop/EventLoop.py
PyProto/eventloop/Events.py
PyProto/eventloop/Exceptions.py
PyProto/eventloop/__init__.py
PyProto/eventloop/engines/__init__.py
PyProto/eventloop/engines/_select.py
PyProto/eventloop/engines/epoll.py
PyProto/eventloop/engines/nullengine.py
PyProto/eventloop/engines/poll.py
PyProto/protocol/IRC.py
PyProto/protocol/__init__.py
PyProto/splitter/Exceptions.py
PyProto/splitter/LineSplitter.py
PyProto/splitter/__init__.py
PyProto/utils/Errors.py
PyProto/utils/Printer.py
PyProto/utils/PriorityMap.py
PyProto/utils/__init__.py
tests/__init__.py
tests/ircprototest.py
tests/pipetest.py
tests/splittertest.py